clipoverlap/__init__.py
clipoverlap/__version.py
clipoverlap/parapysam.py
clipoverlap-1.0.9.data/scripts/clip
clipoverlap-1.0.9.dist-info/DESCRIPTION.rst
clipoverlap-1.0.9.dist-info/METADATA
clipoverlap-1.0.9.dist-info/RECORD
clipoverlap-1.0.9.dist-info/WHEEL
clipoverlap-1.0.9.dist-info/metadata.json
clipoverlap-1.0.9.dist-info/top_level.txt
