Metadata-Version: 2.0
Name: clipoverlap
Version: 1.0.9
Summary: Clips overlapping regions in read mates of SAM/BAM files.
Home-page: https://github.com/innovate-invent/clip
Author: Nolan
Author-email: innovate.invent@gmail.com
License: MIT
Platform: UNKNOWN
Requires-Dist: pysam
Requires-Dist: CigarIterator
